{
  "generated": true,
  "modules": [
    {
      "name": "admin",
      "publicSurface": [
        "getAdminRouteDefinitions"
      ]
    },
    {
      "name": "attendance",
      "publicSurface": [
        "ATTENDANCE_EXCUSE",
        "ATTENDANCE_SHEET_STATE",
        "ATTENDANCE_STATUS",
        "AttendanceExcuse",
        "AttendanceSheetState",
        "AttendanceStatus",
        "attendanceHistoryResponseSchema",
        "attendancePath",
        "attendanceQueryKeys",
        "attendanceRecordResponseSchema",
        "attendanceSheetResponseSchema",
        "attendanceStatusResponseSchema",
        "bulkAttendanceResponseSchema",
        "getAttendanceRouteDefinitions"
      ]
    },
    {
      "name": "auth",
      "publicSurface": [
        "ACCOUNT_STATE",
        "AccountState",
        "AuthMembership",
        "AuthUser",
        "CurrentUserQueryOptions",
        "CurrentUserQueryView",
        "EffectivePermissionsView",
        "LogoutMutationView",
        "SESSION_STATUS",
        "SessionStatus",
        "SessionView",
        "authAckSchema",
        "authQueryKeys",
        "authTokensDtoSchema",
        "authUserDtoSchema",
        "bootstrapSessionFromStoredTokens",
        "buildAuthUser",
        "createAuthTokenRepository",
        "createRefreshExecutor",
        "getAuthRouteDefinitions",
        "getAuthTokenRepository",
        "handleAuthFailure",
        "invitationDetailsDtoSchema",
        "loginResponseSchema",
        "logoutResponseSchema",
        "refreshResponseSchema",
        "revokeOthersResponseSchema",
        "sessionDtoSchema",
        "sessionListResponseSchema",
        "useCurrentUserQuery",
        "useEffectivePermissions",
        "useLogoutMutation",
        "useSession"
      ]
    },
    {
      "name": "dashboard",
      "publicSurface": [
        "DASHBOARD_WIDGET_KIND",
        "DashboardContainer",
        "DashboardWidgetKind",
        "dashboardQueryKeys",
        "dashboardSummaryResponseSchema"
      ]
    },
    {
      "name": "health",
      "publicSurface": [
        "HealthCardContainer",
        "healthQueryKeys",
        "healthResponseSchema"
      ]
    },
    {
      "name": "home",
      "publicSurface": [
        "getHomeRouteDefinitions",
        "getNotFoundRouteDefinition",
        "homePath",
        "welcomePath"
      ]
    },
    {
      "name": "members",
      "publicSurface": [
        "AgeClassification",
        "LIFECYCLE_ACTION",
        "LifecycleAction",
        "MEMBERSHIP_STATUS",
        "MEMBER_AUDIENCE",
        "MEMBER_ROLE",
        "MemberAudience",
        "MemberRole",
        "MembershipStatus",
        "PlayerGender",
        "getMembersRouteDefinitions",
        "memberDirectoryListResponseSchema",
        "memberHistoryResponseSchema",
        "memberProfilePath",
        "memberRolesResponseSchema",
        "memberViewResponseSchema",
        "membersPath",
        "membersQueryKeys",
        "membershipResponseSchema"
      ]
    },
    {
      "name": "practice",
      "publicSurface": [
        "PRACTICE_CHANGE_KIND",
        "PRACTICE_STATUS",
        "PRACTICE_TYPE",
        "PracticeChangeKind",
        "PracticeStatus",
        "PracticeType",
        "RSVP_REASON",
        "RSVP_STATUS",
        "RsvpReason",
        "RsvpStatus",
        "getPracticeRouteDefinitions",
        "practiceQueryKeys",
        "practiceRsvpResponseSchema",
        "practiceSessionListResponseSchema",
        "practiceSessionPath",
        "practiceSessionResponseSchema",
        "practicesPath"
      ]
    },
    {
      "name": "settings",
      "publicSurface": [
        "AppearancePreferences",
        "ThemeToggleView",
        "getSettingsRouteDefinitions",
        "selectIsDarkTheme",
        "settingsPath",
        "useAppearancePreferences",
        "useThemeToggle"
      ]
    },
    {
      "name": "ui-workbench",
      "publicSurface": [
        "getWorkbenchRouteDefinitions",
        "workbenchPath"
      ]
    }
  ]
}
